Metadata-Version: 1.0
Name: statistical-distribution
Version: 1.0
Summary: Gaussian and Binomial distributions
Home-page: UNKNOWN
Author: Rishabh Rajput
Author-email: rrishabh145@gmail.com
License: UNKNOWN
Platform: UNKNOWN
